climtrends/ClimTrendModel.py
climtrends/NoTrendGEVModel.py
climtrends/NoTrendNormalModel.py
climtrends/TrendExponentialModel.py
climtrends/TrendGEVModel.py
climtrends/TrendGammaModel.py
climtrends/TrendNormalModel.py
climtrends/TrendPoissonModel.py
climtrends/TrendTwoMomentNormalModel.py
climtrends/__init__.py
climtrends/utility_functions.py
climtrends-0.0.2.dist-info/LICENSE.txt
climtrends-0.0.2.dist-info/METADATA
climtrends-0.0.2.dist-info/WHEEL
climtrends-0.0.2.dist-info/top_level.txt
climtrends-0.0.2.dist-info/RECORD
