Metadata-Version: 2.1
Name: climtrends
Version: 0.0.2
Summary: A utility for Bayesian trend regression with a variety of statistical models
Home-page: https://github.com/taobrienlbl/climtrends
Author: Travis A. O'Brien
Author-email: obrienta@iu.edu
License: UNKNOWN
Platform: UNKNOWN
Classifier: Programming Language :: Python :: 3
Classifier: Operating System :: OS Independent
Requires-Python: >=3.6
License-File: LICENSE.txt
